vonage_jwt/__init__.py
vonage_jwt/_version.py
vonage_jwt/errors.py
vonage_jwt/jwt.py
vonage_jwt/verify_jwt.py
vonage_jwt-1.1.2.dist-info/METADATA
vonage_jwt-1.1.2.dist-info/WHEEL
vonage_jwt-1.1.2.dist-info/top_level.txt
vonage_jwt-1.1.2.dist-info/RECORD
