Metadata-Version: 2.1
Name: vonage-jwt
Version: 1.1.2
Summary: Tooling for working with JWTs for Vonage APIs in Python.
Author-email: Vonage <devrel@vonage.com>
Project-URL: Homepage, https://github.com/Vonage/vonage-python-sdk
Classifier: Programming Language :: Python
Classifier: Programming Language :: Python :: 3
Classifier: Programming Language :: Python :: 3.8
Classifier: Programming Language :: Python :: 3.9
Classifier: Programming Language :: Python :: 3.10
Classifier: Programming Language :: Python :: 3.11
Classifier: Programming Language :: Python :: 3.12
Classifier: License :: OSI Approved :: Apache Software License
Requires-Python: >=3.8
Requires-Dist: vonage-utils>=1.1.3
Requires-Dist: pyjwt[crypto]>=1.6.4
